.bumpversion.cfg
.coveragerc
.editorconfig
.travis.yml
AUTHORS.rst
CHANGELOG.rst
CONTRIBUTING.rst
LICENSE
MANIFEST.in
README.rst
setup.cfg
setup.py
tox.ini
src/thai_segmenter/__init__.py
src/thai_segmenter/__main__.py
src/thai_segmenter/cli.py
src/thai_segmenter/longlexto.py
src/thai_segmenter/orchid_corpus.py
src/thai_segmenter/sentence.py
src/thai_segmenter/sentence_segmenter.py
src/thai_segmenter/tasks.py
src/thai_segmenter/viterbi.py
src/thai_segmenter/word_processing.py
src/thai_segmenter.egg-info/PKG-INFO
src/thai_segmenter.egg-info/SOURCES.txt
src/thai_segmenter.egg-info/dependency_links.txt
src/thai_segmenter.egg-info/entry_points.txt
src/thai_segmenter.egg-info/not-zip-safe
src/thai_segmenter.egg-info/requires.txt
src/thai_segmenter.egg-info/top_level.txt
src/thai_segmenter/tools/LongLexTo.class
src/thai_segmenter/tools/LongLexTo.class2
src/thai_segmenter/tools/LongLexTo.java
src/thai_segmenter/tools/LongParseTree.class
src/thai_segmenter/tools/LongParseTree.class2
src/thai_segmenter/tools/LongParseTree.java
src/thai_segmenter/tools/LongParseTree.java2
src/thai_segmenter/tools/Trie.class
src/thai_segmenter/tools/Trie.class2
src/thai_segmenter/tools/Trie.java
src/thai_segmenter/tools/custom_dict_word.txt
src/thai_segmenter/tools/lexitron.txt
src/thai_segmenter/tools/lexitron_original.txt
src/thai_segmenter/tools/license.txt
src/thai_segmenter/tools/orchid97.txt
src/thai_segmenter/tools/orchid_words.txt
src/thai_segmenter/tools/pos_map
src/thai_segmenter_webapp/__init__.py
src/thai_segmenter_webapp/__main__.py
src/thai_segmenter_webapp/app.py
src/thai_segmenter_webapp/default_config.py
src/thai_segmenter_webapp/segmenter.py
src/thai_segmenter_webapp/views.py
src/thai_segmenter_webapp/templates/index.html
tests/test_thai_segmenter.py