Metadata-Version: 2.1
Name: thai-segmenter
Version: 0.4.1
Summary: Thai tokenizer, POS-tagger and sentence segmenter.
Home-page: https://github.com/Querela/thai-segmenter
Author: Erik Körner
Author-email: koerner@informatik.uni-leipzig.de
License: MIT license
Project-URL: Changelog, https://github.com/Querela/thai-segmenter/blob/master/CHANGELOG.rst
Project-URL: Issue Tracker, https://github.com/Querela/thai-segmenter/issues
Keywords: thai,nlp,sentence segmentation,tokenize,pos-tag,longlexto,orchid
Platform: UNKNOWN
Classifier: Development Status :: 5 - Production/Stable
Classifier: Intended Audience :: Developers
Classifier: License :: OSI Approved :: MIT License
Classifier: Operating System :: Unix
Classifier: Operating System :: POSIX
Classifier: Operating System :: Microsoft :: Windows
Classifier: Programming Language :: Python
Classifier: Programming Language :: Python :: 3
Classifier: Programming Language :: Python :: 3.5
Classifier: Programming Language :: Python :: 3.6
Classifier: Programming Language :: Python :: 3.7
Classifier: Programming Language :: Python :: Implementation :: CPython
Classifier: Programming Language :: Python :: Implementation :: PyPy
Classifier: Topic :: Utilities
Requires-Python: >=3.4
Provides-Extra: dev
Provides-Extra: webapp
